isd_fetch-0.1.8.dist-info/licenses/LICENSE
pyisd/__init__.py
pyisd/_isd_lite.py
pyisd/misc/__init__.py
pyisd/misc/_misc.py
tests/test_isd_lite.py
isd_fetch-0.1.8.dist-info/METADATA
isd_fetch-0.1.8.dist-info/WHEEL
isd_fetch-0.1.8.dist-info/top_level.txt
isd_fetch-0.1.8.dist-info/RECORD
