Metadata-Version: 2.4
Name: isd-fetch
Version: 0.1.8
Summary: A Python package for fetching ISD Lite data: weather data from NOAA all over the world.
Author: Cyril Joly
License: BSD 3-Clause License
Keywords: ISD Lite,weather data,NOAA
Classifier: Programming Language :: Python :: 3
Classifier: License :: OSI Approved :: MIT License
Classifier: Operating System :: OS Independent
Requires-Python: >=3.7
License-File: LICENSE
Requires-Dist: geopandas
Requires-Dist: tqdm
Dynamic: license-file
